create_test_posts.py
src/clouds/__init__.py
src/clouds/esg.py
src/clouds/main.py
src/clouds/netzero.py
src/clouds/new_cleaning.py
src/clouds/stopword_funcs.py
src/clouds/wordcloud_func.py
cloudvis-0.0.20.dist-info/METADATA
cloudvis-0.0.20.dist-info/WHEEL
cloudvis-0.0.20.dist-info/RECORD
