Metadata-Version: 2.1
Name: cloudVis
Version: 0.0.20
Project-URL: Homepage, https://gitlab.com/susmon/visualisation-scripts
Project-URL: Bug Tracker, https://gitlab.com/susmon/visualization-scripts/issues
Author-email: Philip Dunn <philip@susmon.com>
Classifier: License :: OSI Approved :: MIT License
Classifier: Operating System :: OS Independent
Classifier: Programming Language :: Python :: 3
Requires-Python: >=3.7
Requires-Dist: matplotlib
Requires-Dist: numpy
Requires-Dist: openpyxl
Requires-Dist: pandas
Requires-Dist: wordcloud
